README.md
setup.cfg
setup.py
app/__init__.py
app/helpers/__init__.py
app/helpers/reading_params.py
app/scripts/__init__.py
app/scripts/catxlsx.py
catxls.egg-info/PKG-INFO
catxls.egg-info/SOURCES.txt
catxls.egg-info/dependency_links.txt
catxls.egg-info/entry_points.txt
catxls.egg-info/requires.txt
catxls.egg-info/top_level.txt