Metadata-Version: 1.1
Name: catxls
Version: 0.0.2
Summary: read xls, xlsx on server
Home-page: https://github.com/huongnhdh/catxls.git
Author: huongnhd
Author-email: huong.nhdh@gmail.com
License: MIT
Download-URL: https://github.com/huongnhdh/catxls/archive/v_002.tar.gz
Keywords: xls,xlsx,cat xlsx,server
Platform: UNKNOWN
Classifier: Development Status :: 4 - Beta
Classifier: Intended Audience :: System Administrators
Classifier: Topic :: System :: System Shells
Classifier: License :: OSI Approved :: MIT License
Classifier: Programming Language :: Python :: 3
Classifier: Programming Language :: Python :: 3.4
Classifier: Programming Language :: Python :: 3.5
Classifier: Programming Language :: Python :: 3.6
